[
    {
        "id": "1",
        "firstName": "Siddharth",
        "lastName":"Kamlekar",
        "username":"siddharth0304",
        "password":"12345",
        "email":"saisiddu02@gmail.com",
        "phone":"6302372523",
        "aboutYourself": "Passionate Software Developer",
        "linkedIn":"https://www.linkedin.com/in/siddharthkamlekar/",
        "instagram":"https://www.instagram.com/siddharthkamlekar/profilecard/?igsh=MWkzMzZsODBhMHFvdw==",
        "twitter":"https://x.com/Siddharth4311?t=O4vn9A6F0xWvyCePjqYpJw&s=08 ",
        "image":"https://media.licdn.com/dms/image/v2/D5603AQH1eI2fZiu-Tg/profile-displayphoto-shrink_800_800/profile-displayphoto-shrink_800_800/0/1699368135865?e=1736380800&v=beta&t=bXNbx7tvLlec-KqnjcAK9H-Dt8exjS_Yg3HPyhrmqog",
        "coursesEnrolled":[],
        "userReviews":[]
    },
    {
        "id": "2",
        "firstName": "Donald",
        "lastName": "Trump",
        "username":"president47",
        "password":"12345",
        "email": "donald.trump@example.com",
        "phone": "5551234567",
        "aboutYourself": "A tech enthusiast and aspiring full-stack developer.",
        "linkedIn": "",
        "instagram": "",
        "twitter": "",
        "image": "https://encrypted-tbn0.gstatic.com/images?q=tbn:ANd9GcS1MWm4Uc-yhWB5bkRg8r_Vy6ueABFtDb_qSA&s",
        "coursesEnrolled": [],
        "userReviews":[]
    },
    {
        "id": "3",
        "firstName": "Salman",
        "lastName": "Khan",
        "username":"salman_can",
        "password":"12345",
        "email": "salman.khan@example.com",
        "phone": "5559876543",
        "aboutYourself": "Data scientist with a passion for machine learning and AI.",
        "linkedIn": "",
        "instagram": "",
        "twitter": "",
        "image": "https://cf-img-a-in.tosshub.com/sites/visualstory/wp/2024/08/salman-khan-19.jpg?size=*:900",
        "coursesEnrolled": [],
        "userReviews":[]
    },
    {
        "id": "4",
        "firstName": "Madhuri",
        "lastName": "Dixit",
        "username":"best_dancer",
        "password":"12345",
        "email": "madhuri.dixit@example.com",
        "phone": "5554567890",
        "aboutYourself": "Cybersecurity analyst aiming to deepen knowledge in network security.",
        "linkedIn": "",
        "instagram": "",
        "twitter": "",
        "image": "https://upload.wikimedia.org/wikipedia/commons/thumb/6/6b/Madhuri_Dixit_in_November_2022.jpg/800px-Madhuri_Dixit_in_November_2022.jpg",
        "coursesEnrolled": [],
        "userReviews":[]
    },
    {
        "id": "5",
        "firstName": "John",
        "lastName": "Wick",
        "username":"babayaga",
        "password":"12345",
        "email": "john.wick@example.com",
        "phone": "5556543210",
        "aboutYourself": "Business analyst with a focus on data visualization.",
        "linkedIn": "",
        "instagram": "",
        "twitter": "",
        "image": "https://deadline.com/wp-content/uploads/2023/03/Keanu-Reeves-john-wick-4.jpg",
        "coursesEnrolled": [],
        "userReviews":[]
    }
]